nummus/__init__.py
nummus/exceptions.py
nummus/global_config.py
nummus/main.py
nummus/portfolio.py
nummus/sql.py
nummus/utils.py
nummus/version.py
nummus/web.py
nummus/web_assets.py
nummus/commands/__init__.py
nummus/commands/backup.py
nummus/commands/base.py
nummus/commands/change_password.py
nummus/commands/clean.py
nummus/commands/create.py
nummus/commands/export.py
nummus/commands/health.py
nummus/commands/import_files.py
nummus/commands/migrate.py
nummus/commands/summarize.py
nummus/commands/unlock.py
nummus/commands/update_assets.py
nummus/controllers/__init__.py
nummus/controllers/accounts.py
nummus/controllers/allocation.py
nummus/controllers/assets.py
nummus/controllers/auth.py
nummus/controllers/base.py
nummus/controllers/budgeting.py
nummus/controllers/common.py
nummus/controllers/emergency_fund.py
nummus/controllers/health.py
nummus/controllers/import_file.py
nummus/controllers/income.py
nummus/controllers/labels.py
nummus/controllers/net_worth.py
nummus/controllers/performance.py
nummus/controllers/settings.py
nummus/controllers/spending.py
nummus/controllers/transaction_categories.py
nummus/controllers/transactions.py
nummus/encryption/__init__.py
nummus/encryption/aes.py
nummus/encryption/base.py
nummus/encryption/top.py
nummus/health_checks/__init__.py
nummus/health_checks/base.py
nummus/health_checks/category_direction.py
nummus/health_checks/database_integrity.py
nummus/health_checks/duplicate_transactions.py
nummus/health_checks/empty_fields.py
nummus/health_checks/missing_asset_link.py
nummus/health_checks/missing_valuations.py
nummus/health_checks/outlier_asset_price.py
nummus/health_checks/overdrawn_accounts.py
nummus/health_checks/top.py
nummus/health_checks/typos.py
nummus/health_checks/unbalanced_transfers.py
nummus/health_checks/uncleared_transactions.py
nummus/health_checks/unnecessary_slits.py
nummus/health_checks/unused_categories.py
nummus/importers/__init__.py
nummus/importers/base.py
nummus/importers/raw_csv.py
nummus_financial-0.16.0.dist-info/licenses/LICENSE
nummus_financial-0.16.0.dist-info/METADATA
nummus_financial-0.16.0.dist-info/WHEEL
nummus_financial-0.16.0.dist-info/entry_points.txt
nummus_financial-0.16.0.dist-info/top_level.txt
nummus_financial-0.16.0.dist-info/RECORD
