Metadata-Version: 2.4
Name: nummus-financial
Version: 0.16.0
Summary: A personal financial information aggregator and planning tool
Author-email: Bradley Davis <me@bradleydavis.tech>
License-Expression: MIT
Project-URL: Homepage, https://github.com/WattsUp/nummus
Project-URL: Repository, https://github.com/WattsUp/nummus.git
Project-URL: Issues, https://github.com/WattsUp/nummus/issues
Classifier: Programming Language :: Python :: 3
Classifier: Operating System :: OS Independent
Classifier: Development Status :: 4 - Beta
Classifier: Intended Audience :: Financial and Insurance Industry
Classifier: Intended Audience :: End Users/Desktop
Classifier: Topic :: Office/Business :: Financial
Classifier: Topic :: Office/Business :: Financial :: Accounting
Classifier: Programming Language :: Python :: 3.12
Classifier: Programming Language :: Python :: 3.13
Requires-Python: >=3.12
License-File: LICENSE
Requires-Dist: sqlalchemy>=2
Requires-Dist: gevent
Requires-Dist: colorama
Requires-Dist: rapidfuzz
Requires-Dist: flask>=3
Requires-Dist: flask-assets
Requires-Dist: flask-login
Requires-Dist: pdfplumber
Requires-Dist: yfinance>=0.2.54
Requires-Dist: pyspellchecker>=0.8.3
Requires-Dist: tqdm
Requires-Dist: argcomplete
Requires-Dist: scipy
Requires-Dist: emoji
Requires-Dist: prometheus-flask-exporter
Requires-Dist: packaging
Provides-Extra: encrypt
Requires-Dist: sqlcipher3-binary; extra == "encrypt"
Requires-Dist: Cipher; extra == "encrypt"
Requires-Dist: pycryptodomex; extra == "encrypt"
Provides-Extra: deploy
Requires-Dist: gunicorn; extra == "deploy"
Provides-Extra: test
Requires-Dist: pytest; extra == "test"
Requires-Dist: coverage; extra == "test"
Requires-Dist: numpy; extra == "test"
Requires-Dist: time-machine; extra == "test"
Requires-Dist: tomli; extra == "test"
Requires-Dist: numpy-financial; extra == "test"
Requires-Dist: pytailwindcss; extra == "test"
Requires-Dist: jsmin; extra == "test"
Provides-Extra: dev
Requires-Dist: nummus-financial[deploy,test]; extra == "dev"
Requires-Dist: ruff>=0.14.13; extra == "dev"
Requires-Dist: codespell>=2.4.1; extra == "dev"
Requires-Dist: black>=25.9; extra == "dev"
Requires-Dist: isort; extra == "dev"
Requires-Dist: pre-commit; extra == "dev"
Requires-Dist: djlint>=1.36.4; extra == "dev"
Requires-Dist: pyright>=1.1.402; extra == "dev"
Requires-Dist: taplo; extra == "dev"
Provides-Extra: build
Requires-Dist: build; extra == "build"
Provides-Extra: build-docker
Requires-Dist: nummus-financial[build,encrypt]; extra == "build-docker"
Requires-Dist: setuptools-scm>=8; extra == "build-docker"
Dynamic: license-file
